quicksettings/__init__.py
quicksettings/base.py
quicksettings/utils.py
quicksettings-1.1.1.dist-info/METADATA
quicksettings-1.1.1.dist-info/WHEEL
quicksettings-1.1.1.dist-info/licenses/LICENSE
quicksettings-1.1.1.dist-info/RECORD
