Metadata-Version: 2.3
Name: quicksettings
Version: 1.1.1
Summary: Manage python application config with ease.
Author-email: mvbosch <michael@vonbosch.co.za>
Requires-Python: >=3.9
